synping/__init__.py
synping/synping.py
synping-1.1.dist-info/METADATA
synping-1.1.dist-info/WHEEL
synping-1.1.dist-info/entry_points.txt
synping-1.1.dist-info/licenses/LICENSE
synping-1.1.dist-info/RECORD
