Metadata-Version: 2.3
Name: synping
Version: 1.1
Summary: Ping hosts using tcp syn packets
Project-URL: Homepage, https://github.com/pdrb/synping
Author-email: Pedro Gonring <pedro@bigode.net>
License-File: LICENSE
Keywords: ping,synping,tcp
Classifier: Development Status :: 5 - Production/Stable
Classifier: License :: OSI Approved :: MIT License
Classifier: Operating System :: OS Independent
Classifier: Programming Language :: Python :: 3
Requires-Python: >=3.6
